mlpy/__init__.py
mlpy/agents/fsm.py
mlpy/agents/modules.py
mlpy/agents/world.py
mlpy/agents/__init__.py
mlpy/auxiliary/array.py
mlpy/auxiliary/datasets.py
mlpy/auxiliary/datastructs.py
mlpy/auxiliary/io.py
mlpy/auxiliary/misc.py
mlpy/auxiliary/plotting.py
mlpy/auxiliary/__init__.py
mlpy/cluster/vq.py
mlpy/cluster/__init__.py
mlpy/constants/_constants.py
mlpy/constants/__init__.py
mlpy/environments/gridworld.py
mlpy/environments/nao.py
mlpy/environments/__init__.py
mlpy/environments/webots/controllers/serverc/serverc.py
mlpy/experiments/task.py
mlpy/experiments/__init__.py
mlpy/knowledgerep/__init__.py
mlpy/knowledgerep/cbr/engine.py
mlpy/knowledgerep/cbr/features.py
mlpy/knowledgerep/cbr/methods.py
mlpy/knowledgerep/cbr/similarity.py
mlpy/knowledgerep/cbr/__init__.py
mlpy/learners/__init__.py
mlpy/learners/offline/irl.py
mlpy/learners/offline/__init__.py
mlpy/learners/online/rl.py
mlpy/learners/online/__init__.py
mlpy/libs/classifier.pyd
mlpy/libs/hmmc.pyd
mlpy/libs/noconflict.py
mlpy/libs/__init__.py
mlpy/libs/classifier/array_helper.cc
mlpy/libs/classifier/array_helper.h
mlpy/libs/classifier/c45tree.cc
mlpy/libs/classifier/c45tree.h
mlpy/libs/classifier/classifier.cc
mlpy/libs/classifier/classifier.h
mlpy/libs/classifier/classifier_module.cc
mlpy/libs/classifier/classifier_module.h
mlpy/libs/classifier/coord.cc
mlpy/libs/classifier/coord.h
mlpy/libs/classifier/random.cc
mlpy/libs/classifier/random.h
mlpy/libs/hmmc/hmm.c
mlpy/libs/hmmc/hmm.h
mlpy/libs/hmmc/hmmc_module.c
mlpy/libs/hmmc/hmmc_module.h
mlpy/mdp/discrete.py
mlpy/mdp/distrib.py
mlpy/mdp/stateaction.py
mlpy/mdp/__init__.py
mlpy/mdp/continuous/casml.py
mlpy/mdp/continuous/__init__.py
mlpy/modules/patterns.py
mlpy/modules/__init__.py
mlpy/optimize/algorithms.py
mlpy/optimize/utils.py
mlpy/optimize/__init__.py
mlpy/planners/discrete.py
mlpy/planners/__init__.py
mlpy/planners/explorers/discrete.py
mlpy/planners/explorers/__init__.py
mlpy-0.1.0.dist-info/DESCRIPTION.rst
mlpy-0.1.0.dist-info/METADATA
mlpy-0.1.0.dist-info/metadata.json
mlpy-0.1.0.dist-info/pbr.json
mlpy-0.1.0.dist-info/RECORD
mlpy-0.1.0.dist-info/top_level.txt
mlpy-0.1.0.dist-info/WHEEL
